{
    "draw": 9,
    "recordsTotal": 12,
    "recordsFiltered": 12,
    "data": [
        {
            "Competitors": [
                {
                    "Team": {
                        "Players": [
                            {
                                "TeamId": 981879,
                                "ID": 981876,
                                "ScreenName": "N/A",
                                "ProfileImageVersion": 0,
                                "DisplayName": "Dzianis Chuyanau",
                                "DisplayNameLastFirst": "Chuyanau, Dzianis",
                                "Username": "AnklDen",
                                "LanguageDescription": "English (English)",
                                "PronounsDescription": null
                            }
                        ],
                        "ID": 981879,
                        "Name": null,
                        "StatusDescription": "Active",
                        "IsActive": true
                    },
                    "ID": 1328882,
                    "CheckedIn": null,
                    "ResultConfirmed": "2024-03-05T18:13:59",
                    "SortOrder": 0,
                    "GameByes": 0,
                    "GameWins": 1,
                    "TeamId": 981879,
                    "GameWinsAndGameByes": 1,
                    "Decklists": []
                },
                {
                    "Team": {
                        "Players": [
                            {
                                "TeamId": 981875,
                                "ID": 981872,
                                "ScreenName": "N/A",
                                "ProfileImageVersion": 0,
                                "DisplayName": "Aleksei Raptunovich",
                                "DisplayNameLastFirst": "Raptunovich, Aleksei",
                                "Username": "Alex88",
                                "LanguageDescription": "русский (Russian)",
                                "PronounsDescription": null
                            }
                        ],
                        "ID": 981875,
                        "Name": null,
                        "StatusDescription": "Active",
                        "IsActive": true
                    },
                    "ID": 2832928,
                    "CheckedIn": null,
                    "ResultConfirmed": null,
                    "SortOrder": 1,
                    "GameByes": 0,
                    "GameWins": 2,
                    "TeamId": 981875,
                    "GameWinsAndGameByes": 2,
                    "Decklists": []
                }
            ],
            "ByeReason": null,
            "LossReason": null,
            "RoundName": null,
            "DateCreated": "2024-04-19T13:22:21",
            "Type": 0,
            "FeatureMatch": false,
            "HasResult": true,
            "TimeExtended": false,
            "MatchesPublished": true,
            "RoundNumber": 2,
            "GameDraws": 0,
            "PodNumber": null,
            "SortOrder": null,
            "TableNumber": 1,
            "TimeExtensionMinutes": null,
            "PhaseId": 61841,
            "RoundId": 219231,
            "TournamentId": 65519,
            "Format": "Standard",
            "Guid": "aee384ca-fc8b-4de1-be1b-b12a011dc949",
            "TableLocation": null,
            "TableSection": null,
            "ByeReasonDescription": null,
            "LossReasonDescription": null,
            "ResultString": "Aleksei Raptunovich won 2-1-0",
            "RoundDescription": "Round 2",
            "TableNumberDescription": "1",
            "TypeDescription": "Best of Three",
            "FormatDescription": "Standard"
        },
        {
            "Competitors": [
                {
                    "Team": {
                        "Players": [
                            {
                                "TeamId": 981856,
                                "ID": 981853,
                                "ScreenName": "N/A",
                                "ProfileImageVersion": 3,
                                "DisplayName": "NickLatkovich",
                                "DisplayNameLastFirst": "NickLatkovich",
                                "Username": "NickLatkovich",
                                "LanguageDescription": "English (English)",
                                "PronounsDescription": "He/Him"
                            }
                        ],
                        "ID": 981856,
                        "Name": null,
                        "StatusDescription": "Active",
                        "IsActive": true
                    },
                    "ID": 1328883,
                    "CheckedIn": null,
                    "ResultConfirmed": null,
                    "SortOrder": 0,
                    "GameByes": 0,
                    "GameWins": 1,
                    "TeamId": 981856,
                    "GameWinsAndGameByes": 1,
                    "Decklists": []
                },
                {
                    "Team": {
                        "Players": [
                            {
                                "TeamId": 981860,
                                "ID": 981857,
                                "ScreenName": "N/A",
                                "ProfileImageVersion": 0,
                                "DisplayName": "GlebK",
                                "DisplayNameLastFirst": "GlebK",
                                "Username": "GlebK",
                                "LanguageDescription": "Auto (English)",
                                "PronounsDescription": null
                            }
                        ],
                        "ID": 981860,
                        "Name": null,
                        "StatusDescription": "Active",
                        "IsActive": true
                    },
                    "ID": 2832929,
                    "CheckedIn": null,
                    "ResultConfirmed": null,
                    "SortOrder": 1,
                    "GameByes": 0,
                    "GameWins": 1,
                    "TeamId": 981860,
                    "GameWinsAndGameByes": 1,
                    "Decklists": []
                }
            ],
            "ByeReason": null,
            "LossReason": null,
            "RoundName": null,
            "DateCreated": "2024-04-19T13:22:21",
            "Type": 0,
            "FeatureMatch": false,
            "HasResult": true,
            "TimeExtended": false,
            "MatchesPublished": true,
            "RoundNumber": 2,
            "GameDraws": 0,
            "PodNumber": null,
            "SortOrder": null,
            "TableNumber": 2,
            "TimeExtensionMinutes": null,
            "PhaseId": 61841,
            "RoundId": 219231,
            "TournamentId": 65519,
            "Format": "Standard",
            "Guid": "b8ce9248-2e00-4169-8ae4-b12a011dc94e",
            "TableLocation": null,
            "TableSection": null,
            "ByeReasonDescription": null,
            "LossReasonDescription": null,
            "ResultString": "1-1-0 Draw",
            "RoundDescription": "Round 2",
            "TableNumberDescription": "2",
            "TypeDescription": "Best of Three",
            "FormatDescription": "Standard"
        },
        {
            "Competitors": [
                {
                    "Team": {
                        "Players": [
                            {
                                "TeamId": 981876,
                                "ID": 981873,
                                "ScreenName": "N/A",
                                "ProfileImageVersion": 1,
                                "DisplayName": "Egor Kryshkavets",
                                "DisplayNameLastFirst": "Kryshkavets, Egor",
                                "Username": "Damingez",
                                "LanguageDescription": "Auto (English)",
                                "PronounsDescription": "He/Him"
                            }
                        ],
                        "ID": 981876,
                        "Name": null,
                        "StatusDescription": "Active",
                        "IsActive": true
                    },
                    "ID": 1328884,
                    "CheckedIn": null,
                    "ResultConfirmed": null,
                    "SortOrder": 0,
                    "GameByes": 0,
                    "GameWins": 2,
                    "TeamId": 981876,
                    "GameWinsAndGameByes": 2,
                    "Decklists": []
                },
                {
                    "Team": {
                        "Players": [
                            {
                                "TeamId": 981851,
                                "ID": 981848,
                                "ScreenName": "N/A",
                                "ProfileImageVersion": 0,
                                "DisplayName": "Slava Belezeko",
                                "DisplayNameLastFirst": "Belezeko, Slava",
                                "Username": "Slava_bel",
                                "LanguageDescription": "Auto (English)",
                                "PronounsDescription": null
                            }
                        ],
                        "ID": 981851,
                        "Name": null,
                        "StatusDescription": "Dropped (Staff)",
                        "IsActive": false
                    },
                    "ID": 2832930,
                    "CheckedIn": null,
                    "ResultConfirmed": null,
                    "SortOrder": 1,
                    "GameByes": 0,
                    "GameWins": 0,
                    "TeamId": 981851,
                    "GameWinsAndGameByes": 0,
                    "Decklists": []
                }
            ],
            "ByeReason": null,
            "LossReason": null,
            "RoundName": null,
            "DateCreated": "2024-04-19T13:22:21",
            "Type": 0,
            "FeatureMatch": false,
            "HasResult": true,
            "TimeExtended": false,
            "MatchesPublished": true,
            "RoundNumber": 2,
            "GameDraws": 0,
            "PodNumber": null,
            "SortOrder": null,
            "TableNumber": 3,
            "TimeExtensionMinutes": null,
            "PhaseId": 61841,
            "RoundId": 219231,
            "TournamentId": 65519,
            "Format": "Standard",
            "Guid": "7ab499cb-3226-4bd5-abd1-b12a011dc94e",
            "TableLocation": null,
            "TableSection": null,
            "ByeReasonDescription": null,
            "LossReasonDescription": null,
            "ResultString": "Egor Kryshkavets won 2-0-0",
            "RoundDescription": "Round 2",
            "TableNumberDescription": "3",
            "TypeDescription": "Best of Three",
            "FormatDescription": "Standard"
        },
        {
            "Competitors": [
                {
                    "Team": {
                        "Players": [
                            {
                                "TeamId": 981853,
                                "ID": 981850,
                                "ScreenName": "N/A",
                                "ProfileImageVersion": 0,
                                "DisplayName": "Akel",
                                "DisplayNameLastFirst": "Akel",
                                "Username": "Akel",
                                "LanguageDescription": "русский (Russian)",
                                "PronounsDescription": "He/Him"
                            }
                        ],
                        "ID": 981853,
                        "Name": null,
                        "StatusDescription": "Active",
                        "IsActive": true
                    },
                    "ID": 1328885,
                    "CheckedIn": null,
                    "ResultConfirmed": "2024-03-05T18:07:30",
                    "SortOrder": 0,
                    "GameByes": 0,
                    "GameWins": 1,
                    "TeamId": 981853,
                    "GameWinsAndGameByes": 1,
                    "Decklists": []
                },
                {
                    "Team": {
                        "Players": [
                            {
                                "TeamId": 981863,
                                "ID": 981860,
                                "ScreenName": "N/A",
                                "ProfileImageVersion": 1,
                                "DisplayName": "Роман Кохан",
                                "DisplayNameLastFirst": "Кохан, Роман",
                                "Username": "RomanKohan14",
                                "LanguageDescription": "English (English)",
                                "PronounsDescription": null
                            }
                        ],
                        "ID": 981863,
                        "Name": null,
                        "StatusDescription": "Active",
                        "IsActive": true
                    },
                    "ID": 2832931,
                    "CheckedIn": null,
                    "ResultConfirmed": null,
                    "SortOrder": 1,
                    "GameByes": 0,
                    "GameWins": 2,
                    "TeamId": 981863,
                    "GameWinsAndGameByes": 2,
                    "Decklists": []
                }
            ],
            "ByeReason": null,
            "LossReason": null,
            "RoundName": null,
            "DateCreated": "2024-04-19T13:22:21",
            "Type": 0,
            "FeatureMatch": false,
            "HasResult": true,
            "TimeExtended": false,
            "MatchesPublished": true,
            "RoundNumber": 2,
            "GameDraws": 0,
            "PodNumber": null,
            "SortOrder": null,
            "TableNumber": 4,
            "TimeExtensionMinutes": null,
            "PhaseId": 61841,
            "RoundId": 219231,
            "TournamentId": 65519,
            "Format": "Standard",
            "Guid": "ed7644f2-d1e0-4ab8-ae49-b12a011dc94e",
            "TableLocation": null,
            "TableSection": null,
            "ByeReasonDescription": null,
            "LossReasonDescription": null,
            "ResultString": "Роман Кохан won 2-1-0",
            "RoundDescription": "Round 2",
            "TableNumberDescription": "4",
            "TypeDescription": "Best of Three",
            "FormatDescription": "Standard"
        },
        {
            "Competitors": [
                {
                    "Team": {
                        "Players": [
                            {
                                "TeamId": 981864,
                                "ID": 981861,
                                "ScreenName": "N/A",
                                "ProfileImageVersion": 1,
                                "DisplayName": "OMGProfunny",
                                "DisplayNameLastFirst": "OMGProfunny",
                                "Username": "OMGProfunny",
                                "LanguageDescription": "Auto (English)",
                                "PronounsDescription": null
                            }
                        ],
                        "ID": 981864,
                        "Name": null,
                        "StatusDescription": "Active",
                        "IsActive": true
                    },
                    "ID": 1328886,
                    "CheckedIn": null,
                    "ResultConfirmed": "2024-03-05T17:47:07",
                    "SortOrder": 0,
                    "GameByes": 0,
                    "GameWins": 2,
                    "TeamId": 981864,
                    "GameWinsAndGameByes": 2,
                    "Decklists": []
                },
                {
                    "Team": {
                        "Players": [
                            {
                                "TeamId": 981870,
                                "ID": 981867,
                                "ScreenName": "N/A",
                                "ProfileImageVersion": 0,
                                "DisplayName": "[OMG]Summie",
                                "DisplayNameLastFirst": "[OMG]Summie",
                                "Username": "[OMG]Summie",
                                "LanguageDescription": "Auto (English)",
                                "PronounsDescription": null
                            }
                        ],
                        "ID": 981870,
                        "Name": null,
                        "StatusDescription": "Active",
                        "IsActive": true
                    },
                    "ID": 2832932,
                    "CheckedIn": null,
                    "ResultConfirmed": null,
                    "SortOrder": 1,
                    "GameByes": 0,
                    "GameWins": 0,
                    "TeamId": 981870,
                    "GameWinsAndGameByes": 0,
                    "Decklists": []
                }
            ],
            "ByeReason": null,
            "LossReason": null,
            "RoundName": null,
            "DateCreated": "2024-04-19T13:22:21",
            "Type": 0,
            "FeatureMatch": false,
            "HasResult": true,
            "TimeExtended": false,
            "MatchesPublished": true,
            "RoundNumber": 2,
            "GameDraws": 0,
            "PodNumber": null,
            "SortOrder": null,
            "TableNumber": 5,
            "TimeExtensionMinutes": null,
            "PhaseId": 61841,
            "RoundId": 219231,
            "TournamentId": 65519,
            "Format": "Standard",
            "Guid": "7933ffb9-2cc1-4941-b73d-b12a011dc94e",
            "TableLocation": null,
            "TableSection": null,
            "ByeReasonDescription": null,
            "LossReasonDescription": null,
            "ResultString": "OMGProfunny won 2-0-0",
            "RoundDescription": "Round 2",
            "TableNumberDescription": "5",
            "TypeDescription": "Best of Three",
            "FormatDescription": "Standard"
        },
        {
            "Competitors": [
                {
                    "Team": {
                        "Players": [
                            {
                                "TeamId": 981848,
                                "ID": 981845,
                                "ScreenName": "N/A",
                                "ProfileImageVersion": 0,
                                "DisplayName": "vorotinskyV",
                                "DisplayNameLastFirst": "vorotinskyV",
                                "Username": "vorotinskyV",
                                "LanguageDescription": "Auto (English)",
                                "PronounsDescription": null
                            }
                        ],
                        "ID": 981848,
                        "Name": null,
                        "StatusDescription": "Active",
                        "IsActive": true
                    },
                    "ID": 1328887,
                    "CheckedIn": null,
                    "ResultConfirmed": null,
                    "SortOrder": 0,
                    "GameByes": 0,
                    "GameWins": 2,
                    "TeamId": 981848,
                    "GameWinsAndGameByes": 2,
                    "Decklists": []
                },
                {
                    "Team": {
                        "Players": [
                            {
                                "TeamId": 981838,
                                "ID": 981835,
                                "ScreenName": "N/A",
                                "ProfileImageVersion": 0,
                                "DisplayName": "Петр Кулыба",
                                "DisplayNameLastFirst": "Кулыба, Петр",
                                "Username": "Ifrit56",
                                "LanguageDescription": "Auto (English)",
                                "PronounsDescription": null
                            }
                        ],
                        "ID": 981838,
                        "Name": null,
                        "StatusDescription": "Active",
                        "IsActive": true
                    },
                    "ID": 2832933,
                    "CheckedIn": null,
                    "ResultConfirmed": "2024-03-05T18:03:50",
                    "SortOrder": 1,
                    "GameByes": 0,
                    "GameWins": 1,
                    "TeamId": 981838,
                    "GameWinsAndGameByes": 1,
                    "Decklists": []
                }
            ],
            "ByeReason": null,
            "LossReason": null,
            "RoundName": null,
            "DateCreated": "2024-04-19T13:22:21",
            "Type": 0,
            "FeatureMatch": false,
            "HasResult": true,
            "TimeExtended": false,
            "MatchesPublished": true,
            "RoundNumber": 2,
            "GameDraws": 0,
            "PodNumber": null,
            "SortOrder": null,
            "TableNumber": 6,
            "TimeExtensionMinutes": null,
            "PhaseId": 61841,
            "RoundId": 219231,
            "TournamentId": 65519,
            "Format": "Standard",
            "Guid": "9d86aa79-757c-4190-96eb-b12a011dc94e",
            "TableLocation": null,
            "TableSection": null,
            "ByeReasonDescription": null,
            "LossReasonDescription": null,
            "ResultString": "vorotinskyV won 2-1-0",
            "RoundDescription": "Round 2",
            "TableNumberDescription": "6",
            "TypeDescription": "Best of Three",
            "FormatDescription": "Standard"
        },
        {
            "Competitors": [
                {
                    "Team": {
                        "Players": [
                            {
                                "TeamId": 981866,
                                "ID": 981863,
                                "ScreenName": "N/A",
                                "ProfileImageVersion": 0,
                                "DisplayName": "Egor Snytko",
                                "DisplayNameLastFirst": "Snytko, Egor",
                                "Username": "warded_bye",
                                "LanguageDescription": "Auto (English)",
                                "PronounsDescription": null
                            }
                        ],
                        "ID": 981866,
                        "Name": null,
                        "StatusDescription": "Dropped (Staff)",
                        "IsActive": false
                    },
                    "ID": 1328888,
                    "CheckedIn": null,
                    "ResultConfirmed": null,
                    "SortOrder": 0,
                    "GameByes": 0,
                    "GameWins": 1,
                    "TeamId": 981866,
                    "GameWinsAndGameByes": 1,
                    "Decklists": []
                },
                {
                    "Team": {
                        "Players": [
                            {
                                "TeamId": 981871,
                                "ID": 981868,
                                "ScreenName": "N/A",
                                "ProfileImageVersion": 0,
                                "DisplayName": "Denis Prokofiev",
                                "DisplayNameLastFirst": "Prokofiev, Denis",
                                "Username": "Prokis",
                                "LanguageDescription": "Auto (English)",
                                "PronounsDescription": null
                            }
                        ],
                        "ID": 981871,
                        "Name": null,
                        "StatusDescription": "Dropped (Staff)",
                        "IsActive": false
                    },
                    "ID": 2832934,
                    "CheckedIn": null,
                    "ResultConfirmed": null,
                    "SortOrder": 1,
                    "GameByes": 0,
                    "GameWins": 1,
                    "TeamId": 981871,
                    "GameWinsAndGameByes": 1,
                    "Decklists": []
                }
            ],
            "ByeReason": null,
            "LossReason": null,
            "RoundName": null,
            "DateCreated": "2024-04-19T13:22:21",
            "Type": 0,
            "FeatureMatch": false,
            "HasResult": true,
            "TimeExtended": false,
            "MatchesPublished": true,
            "RoundNumber": 2,
            "GameDraws": 0,
            "PodNumber": null,
            "SortOrder": null,
            "TableNumber": 7,
            "TimeExtensionMinutes": null,
            "PhaseId": 61841,
            "RoundId": 219231,
            "TournamentId": 65519,
            "Format": "Standard",
            "Guid": "354c2530-5760-4e4a-94dc-b12a011dc94e",
            "TableLocation": null,
            "TableSection": null,
            "ByeReasonDescription": null,
            "LossReasonDescription": null,
            "ResultString": "1-1-0 Draw",
            "RoundDescription": "Round 2",
            "TableNumberDescription": "7",
            "TypeDescription": "Best of Three",
            "FormatDescription": "Standard"
        },
        {
            "Competitors": [
                {
                    "Team": {
                        "Players": [
                            {
                                "TeamId": 981859,
                                "ID": 981856,
                                "ScreenName": "N/A",
                                "ProfileImageVersion": 1,
                                "DisplayName": "AndreyG",
                                "DisplayNameLastFirst": "AndreyG",
                                "Username": "AndreyG",
                                "LanguageDescription": "Auto (English)",
                                "PronounsDescription": null
                            }
                        ],
                        "ID": 981859,
                        "Name": null,
                        "StatusDescription": "Active",
                        "IsActive": true
                    },
                    "ID": 1328889,
                    "CheckedIn": null,
                    "ResultConfirmed": null,
                    "SortOrder": 0,
                    "GameByes": 0,
                    "GameWins": 1,
                    "TeamId": 981859,
                    "GameWinsAndGameByes": 1,
                    "Decklists": []
                },
                {
                    "Team": {
                        "Players": [
                            {
                                "TeamId": 981569,
                                "ID": 981566,
                                "ScreenName": "N/A",
                                "ProfileImageVersion": 0,
                                "DisplayName": "m1nki",
                                "DisplayNameLastFirst": "m1nki",
                                "Username": "m1nki",
                                "LanguageDescription": "Auto (English)",
                                "PronounsDescription": "Ze/zir"
                            }
                        ],
                        "ID": 981569,
                        "Name": null,
                        "StatusDescription": "Dropped (Staff)",
                        "IsActive": false
                    },
                    "ID": 2832935,
                    "CheckedIn": null,
                    "ResultConfirmed": null,
                    "SortOrder": 1,
                    "GameByes": 0,
                    "GameWins": 1,
                    "TeamId": 981569,
                    "GameWinsAndGameByes": 1,
                    "Decklists": []
                }
            ],
            "ByeReason": null,
            "LossReason": null,
            "RoundName": null,
            "DateCreated": "2024-04-19T13:22:21",
            "Type": 0,
            "FeatureMatch": false,
            "HasResult": true,
            "TimeExtended": false,
            "MatchesPublished": true,
            "RoundNumber": 2,
            "GameDraws": 0,
            "PodNumber": null,
            "SortOrder": null,
            "TableNumber": 8,
            "TimeExtensionMinutes": null,
            "PhaseId": 61841,
            "RoundId": 219231,
            "TournamentId": 65519,
            "Format": "Standard",
            "Guid": "028cd0f9-1b3a-426b-b6a9-b12a011dc94e",
            "TableLocation": null,
            "TableSection": null,
            "ByeReasonDescription": null,
            "LossReasonDescription": null,
            "ResultString": "1-1-0 Draw",
            "RoundDescription": "Round 2",
            "TableNumberDescription": "8",
            "TypeDescription": "Best of Three",
            "FormatDescription": "Standard"
        },
        {
            "Competitors": [
                {
                    "Team": {
                        "Players": [
                            {
                                "TeamId": 981854,
                                "ID": 981851,
                                "ScreenName": "N/A",
                                "ProfileImageVersion": 0,
                                "DisplayName": "wwwcardPrince18",
                                "DisplayNameLastFirst": "wwwcardPrince18",
                                "Username": "wwwcardPrince18",
                                "LanguageDescription": "Auto (English)",
                                "PronounsDescription": null
                            }
                        ],
                        "ID": 981854,
                        "Name": null,
                        "StatusDescription": "Active",
                        "IsActive": true
                    },
                    "ID": 1328890,
                    "CheckedIn": null,
                    "ResultConfirmed": null,
                    "SortOrder": 0,
                    "GameByes": 0,
                    "GameWins": 1,
                    "TeamId": 981854,
                    "GameWinsAndGameByes": 1,
                    "Decklists": []
                },
                {
                    "Team": {
                        "Players": [
                            {
                                "TeamId": 981850,
                                "ID": 981847,
                                "ScreenName": "N/A",
                                "ProfileImageVersion": 2,
                                "DisplayName": "Alexsandr  Golovskiy",
                                "DisplayNameLastFirst": "Golovskiy, Alexsandr ",
                                "Username": "Sasha33",
                                "LanguageDescription": "русский (Russian)",
                                "PronounsDescription": null
                            }
                        ],
                        "ID": 981850,
                        "Name": null,
                        "StatusDescription": "Active",
                        "IsActive": true
                    },
                    "ID": 2832936,
                    "CheckedIn": null,
                    "ResultConfirmed": null,
                    "SortOrder": 1,
                    "GameByes": 0,
                    "GameWins": 2,
                    "TeamId": 981850,
                    "GameWinsAndGameByes": 2,
                    "Decklists": []
                }
            ],
            "ByeReason": null,
            "LossReason": null,
            "RoundName": null,
            "DateCreated": "2024-04-19T13:22:21",
            "Type": 0,
            "FeatureMatch": false,
            "HasResult": true,
            "TimeExtended": false,
            "MatchesPublished": true,
            "RoundNumber": 2,
            "GameDraws": 0,
            "PodNumber": null,
            "SortOrder": null,
            "TableNumber": 9,
            "TimeExtensionMinutes": null,
            "PhaseId": 61841,
            "RoundId": 219231,
            "TournamentId": 65519,
            "Format": "Standard",
            "Guid": "a3578620-d345-4af4-a7dd-b12a011dc94e",
            "TableLocation": null,
            "TableSection": null,
            "ByeReasonDescription": null,
            "LossReasonDescription": null,
            "ResultString": "Alexsandr  Golovskiy won 2-1-0",
            "RoundDescription": "Round 2",
            "TableNumberDescription": "9",
            "TypeDescription": "Best of Three",
            "FormatDescription": "Standard"
        },
        {
            "Competitors": [
                {
                    "Team": {
                        "Players": [
                            {
                                "TeamId": 981759,
                                "ID": 981756,
                                "ScreenName": "N/A",
                                "ProfileImageVersion": 0,
                                "DisplayName": "Ilya Bogdan",
                                "DisplayNameLastFirst": "Bogdan, Ilya",
                                "Username": "Barbossa",
                                "LanguageDescription": "Auto (English)",
                                "PronounsDescription": null
                            }
                        ],
                        "ID": 981759,
                        "Name": null,
                        "StatusDescription": "Dropped (Staff)",
                        "IsActive": false
                    },
                    "ID": 1328891,
                    "CheckedIn": null,
                    "ResultConfirmed": "2024-03-05T18:09:40",
                    "SortOrder": 0,
                    "GameByes": 0,
                    "GameWins": 1,
                    "TeamId": 981759,
                    "GameWinsAndGameByes": 1,
                    "Decklists": []
                },
                {
                    "Team": {
                        "Players": [
                            {
                                "TeamId": 981874,
                                "ID": 981871,
                                "ScreenName": "N/A",
                                "ProfileImageVersion": 0,
                                "DisplayName": "Maksim Martseniuk",
                                "DisplayNameLastFirst": "Martseniuk, Maksim",
                                "Username": "qvertion",
                                "LanguageDescription": "Auto (English)",
                                "PronounsDescription": null
                            }
                        ],
                        "ID": 981874,
                        "Name": null,
                        "StatusDescription": "Active",
                        "IsActive": true
                    },
                    "ID": 2832937,
                    "CheckedIn": null,
                    "ResultConfirmed": null,
                    "SortOrder": 1,
                    "GameByes": 0,
                    "GameWins": 2,
                    "TeamId": 981874,
                    "GameWinsAndGameByes": 2,
                    "Decklists": []
                }
            ],
            "ByeReason": null,
            "LossReason": null,
            "RoundName": null,
            "DateCreated": "2024-04-19T13:22:21",
            "Type": 0,
            "FeatureMatch": false,
            "HasResult": true,
            "TimeExtended": false,
            "MatchesPublished": true,
            "RoundNumber": 2,
            "GameDraws": 0,
            "PodNumber": null,
            "SortOrder": null,
            "TableNumber": 10,
            "TimeExtensionMinutes": null,
            "PhaseId": 61841,
            "RoundId": 219231,
            "TournamentId": 65519,
            "Format": "Standard",
            "Guid": "1b719584-7206-4496-a31c-b12a011dc94e",
            "TableLocation": null,
            "TableSection": null,
            "ByeReasonDescription": null,
            "LossReasonDescription": null,
            "ResultString": "Maksim Martseniuk won 2-1-0",
            "RoundDescription": "Round 2",
            "TableNumberDescription": "10",
            "TypeDescription": "Best of Three",
            "FormatDescription": "Standard"
        },
        {
            "Competitors": [
                {
                    "Team": {
                        "Players": [
                            {
                                "TeamId": 981868,
                                "ID": 981865,
                                "ScreenName": "N/A",
                                "ProfileImageVersion": 0,
                                "DisplayName": "Yauheni Ihnatsik",
                                "DisplayNameLastFirst": "Ihnatsik, Yauheni",
                                "Username": "McRais",
                                "LanguageDescription": "Auto (English)",
                                "PronounsDescription": null
                            }
                        ],
                        "ID": 981868,
                        "Name": null,
                        "StatusDescription": "Active",
                        "IsActive": true
                    },
                    "ID": 1328892,
                    "CheckedIn": null,
                    "ResultConfirmed": "2024-03-05T17:45:54",
                    "SortOrder": 0,
                    "GameByes": 0,
                    "GameWins": 0,
                    "TeamId": 981868,
                    "GameWinsAndGameByes": 0,
                    "Decklists": []
                },
                {
                    "Team": {
                        "Players": [
                            {
                                "TeamId": 981852,
                                "ID": 981849,
                                "ScreenName": "N/A",
                                "ProfileImageVersion": 0,
                                "DisplayName": "Илья Лашкин",
                                "DisplayNameLastFirst": "Лашкин, Илья",
                                "Username": "SoXa",
                                "LanguageDescription": "Auto (English)",
                                "PronounsDescription": null
                            }
                        ],
                        "ID": 981852,
                        "Name": null,
                        "StatusDescription": "Active",
                        "IsActive": true
                    },
                    "ID": 2832938,
                    "CheckedIn": null,
                    "ResultConfirmed": null,
                    "SortOrder": 1,
                    "GameByes": 0,
                    "GameWins": 2,
                    "TeamId": 981852,
                    "GameWinsAndGameByes": 2,
                    "Decklists": []
                }
            ],
            "ByeReason": null,
            "LossReason": null,
            "RoundName": null,
            "DateCreated": "2024-04-19T13:22:21",
            "Type": 0,
            "FeatureMatch": false,
            "HasResult": true,
            "TimeExtended": false,
            "MatchesPublished": true,
            "RoundNumber": 2,
            "GameDraws": 0,
            "PodNumber": null,
            "SortOrder": null,
            "TableNumber": 11,
            "TimeExtensionMinutes": null,
            "PhaseId": 61841,
            "RoundId": 219231,
            "TournamentId": 65519,
            "Format": "Standard",
            "Guid": "f2235c37-a1b7-4da0-aee1-b12a011dc94e",
            "TableLocation": null,
            "TableSection": null,
            "ByeReasonDescription": null,
            "LossReasonDescription": null,
            "ResultString": "Илья Лашкин won 2-0-0",
            "RoundDescription": "Round 2",
            "TableNumberDescription": "11",
            "TypeDescription": "Best of Three",
            "FormatDescription": "Standard"
        },
        {
            "Competitors": [
                {
                    "Team": {
                        "Players": [
                            {
                                "TeamId": 981857,
                                "ID": 981854,
                                "ScreenName": "N/A",
                                "ProfileImageVersion": 0,
                                "DisplayName": "DiaI",
                                "DisplayNameLastFirst": "DiaI",
                                "Username": "DiaI",
                                "LanguageDescription": "Auto (English)",
                                "PronounsDescription": null
                            }
                        ],
                        "ID": 981857,
                        "Name": null,
                        "StatusDescription": "Dropped (Staff)",
                        "IsActive": false
                    },
                    "ID": 1328893,
                    "CheckedIn": null,
                    "ResultConfirmed": null,
                    "SortOrder": 0,
                    "GameByes": 0,
                    "GameWins": 0,
                    "TeamId": 981857,
                    "GameWinsAndGameByes": 0,
                    "Decklists": []
                },
                {
                    "Team": {
                        "Players": [
                            {
                                "TeamId": 981793,
                                "ID": 981790,
                                "ScreenName": "N/A",
                                "ProfileImageVersion": 0,
                                "DisplayName": "ispinyouround",
                                "DisplayNameLastFirst": "ispinyouround",
                                "Username": "ispinyouround",
                                "LanguageDescription": "English (English)",
                                "PronounsDescription": null
                            }
                        ],
                        "ID": 981793,
                        "Name": null,
                        "StatusDescription": "Active",
                        "IsActive": true
                    },
                    "ID": 2832939,
                    "CheckedIn": null,
                    "ResultConfirmed": "2024-03-05T18:07:28",
                    "SortOrder": 1,
                    "GameByes": 0,
                    "GameWins": 2,
                    "TeamId": 981793,
                    "GameWinsAndGameByes": 2,
                    "Decklists": []
                }
            ],
            "ByeReason": null,
            "LossReason": null,
            "RoundName": null,
            "DateCreated": "2024-04-19T13:22:21",
            "Type": 0,
            "FeatureMatch": false,
            "HasResult": true,
            "TimeExtended": false,
            "MatchesPublished": true,
            "RoundNumber": 2,
            "GameDraws": 0,
            "PodNumber": null,
            "SortOrder": null,
            "TableNumber": 12,
            "TimeExtensionMinutes": null,
            "PhaseId": 61841,
            "RoundId": 219231,
            "TournamentId": 65519,
            "Format": "Standard",
            "Guid": "a9d686ce-126a-47b3-b043-b12a011dc94e",
            "TableLocation": null,
            "TableSection": null,
            "ByeReasonDescription": null,
            "LossReasonDescription": null,
            "ResultString": "ispinyouround won 2-0-0",
            "RoundDescription": "Round 2",
            "TableNumberDescription": "12",
            "TypeDescription": "Best of Three",
            "FormatDescription": "Standard"
        }
    ],
    "download": null
}